{"escapees":{"humans":{"1":{"name":"Alexadre Magnus Segundo","ckey":"alexalbright","location":"Emergency Shuttle","health":82.58,"job":"Legion Slave","species":"Human"},"2":{"name":"Baam Frest","ckey":"gabrieldoombr","location":"Emergency Shuttle","health":86.33,"job":"NCR Corporal","species":"Human"},"3":{"name":"Bob Merlin","ckey":"guizog","location":"Emergency Shuttle","health":100,"job":"Outlaw","species":"Human"},"4":{"name":"Dav Jones","ckey":"luciam","location":"Emergency Shuttle","health":85.5,"job":"NCR Ranger","species":"Skeleton"},"5":{"name":"Guilherme Eva (as Owen Davis)","ckey":"guilhty","location":"Emergency Shuttle","health":80.5,"job":"Outlaw","species":"Human"},"6":{"name":"Hunter Simmons","ckey":"2006f","location":"Emergency Shuttle","health":66.34,"job":"Enclave Sergant","species":"Human"},"7":{"name":"John Wick","ckey":"darkpudding","location":"Emergency Shuttle","health":97.51,"job":"NCR Combat Medic","species":"Human"},"8":{"name":"Luicio Notav","ckey":"jhonatanlima","location":"Emergency Shuttle","health":76.59,"job":"NCR Ranger","species":"Human"},"9":{"name":"Miguel Hastings","ckey":"eversonblr","location":"Emergency Shuttle","health":40.82,"job":"Head Scribe","species":"Human"},"10":{"name":"Rebeckah Prevatt","ckey":"corvopimpolho","location":"CentCom Recovery Ship","health":84.67,"job":"Initiate","species":"Human"},"11":{"name":"Tullia","ckey":"garwarmin","location":"Emergency Shuttle","health":38.25,"job":"Legion Slave","species":"Human"},"12":{"name":"Alana Rader","ckey":"nickenzo12345","location":"Emergency Shuttle","health":80.56,"job":"Wastelander","species":"Human"},"13":{"name":"Yuri Daruski","ckey":"fidgetybacchus","location":"Emergency Shuttle","health":92.16,"job":"Wastelander","species":"Human"},"14":{"name":"Rayan Lindgrey","ckey":"inicialplayss","location":"Emergency Shuttle","health":100,"job":"Wastelander","species":"Human"}},"silicons":{"1":{"name":"G3","ckey":"malocous","location":"Emergency Shuttle","health":100,"module":"Medical"}},"others":[],"npcs":{"brain":1,"Medibot":3,"Mysterious Medibot":1}},"abandoned":{"humans":{"1":{"name":"Alana Rader","ckey":"nickenzo12345","location":"Wasteland","health":-100,"job":"Star Paladin","species":"Human"},"2":{"name":"Bob Loureiro","ckey":"degusta00","location":"Tunnel","health":-105.62,"job":"Wastelander","species":"Human"},"3":{"name":"Courier","ckey":"sondtheanime","location":"Brotherhood of Steel RnD Department","health":100,"job":"Head Knight","species":"Human"},"4":{"name":"Dr Oswald Casket","ckey":"dantethanatos","location":"Brotherhood of Steel Medbay","health":100,"job":"Proctor","species":"Human"},"5":{"name":"Elias Ivanov","ckey":"albertovinhofino","location":"Tunnel","health":-100.5,"job":"Vault-tec Doctor","species":"Human"},"6":{"name":"Felix Inculta","ckey":"fidgetybacchus","location":"Bunker","health":-100,"job":"Legion Vexillarius","species":"Human"},"7":{"name":"Garrety Wells","ckey":"zero9e1","location":"Brotherhood of Steel Operations Department","health":92.5,"job":"Druid","species":"Human"},"8":{"name":"Gilgimus Victorus","ckey":"xenotin","location":"NCR","health":89.75,"job":"NCR Sergeant First Class","species":"Human"},"9":{"name":"Hadley Barrett","ckey":"n0fun","location":"Wasteland","health":100,"job":"Proctor","species":"Human"},"10":{"name":"Isabellus Enderlus","ckey":"xenotin","location":"Legion","health":-100,"job":"Legion Veteran Decanus","species":"Felinid"},"11":{"name":"John Grave","ckey":"gatossj","location":"Vault","health":93.01,"job":"Vault-tec Scientist","species":"Human"},"12":{"name":"Joseph Joestar","ckey":"shirozinha","location":"Brotherhood of Steel Operations Department","health":87.53,"job":"Veteran Legionary","species":"Skeleton"},"13":{"name":"Keziah Wright","ckey":"aert","location":"Wasteland","health":100,"job":"NCR Corporal","species":"Human"},"14":{"name":"Lalla Kuznetsov (as Tio Osso)","ckey":"nickenzo12345","location":"Bunker","health":-100,"job":"Outlaw","species":"Human"},"15":{"name":"Luciam D'Luker","ckey":"luciam","location":"Bunker","health":-112.09,"job":"Outlaw","species":"Human"},"16":{"name":"Markus Stigat","ckey":"jhonatanlima","location":"Tunnel","health":-100,"job":"Wastelander","species":"Human"},"17":{"name":"Michael Rose","ckey":"richardcampi","location":"Followers of the Apocalypse","health":-100.18,"job":"Wastelander","species":"Ghoul"},"18":{"name":"Nickolas Priebe","ckey":"coffeemasterori","location":"Bunker","health":-100.42,"job":"Wastelander","species":"Human"},"19":{"name":"Nycolly Kawatsuto","ckey":"matheusgp9999","location":"Wasteland","health":100,"job":"Wastelander","species":"Human"},"20":{"name":"Nykix Nyty","ckey":"matheusgp9999","location":"Wasteland","health":-100,"job":"Wastelander","species":"Human"},"21":{"name":"Owen Davis","ckey":"richardcampi","location":"Village","health":100,"job":"Wastelander","species":"Human"},"22":{"name":"Rayner Rifler","ckey":"corvopimpolho","location":"Brotherhood of Steel Medbay","health":-157.5,"job":"Outlaw","species":"Human"},"23":{"name":"Rodrigo Weisgarber","ckey":"mastrodonteplays","location":"Wasteland","health":-101.89,"job":"Detective","species":"Human"},"24":{"name":"Tio Osso","ckey":"shirozinha","location":"Wasteland","health":-549.15,"job":"Legion Venator","species":"Skeleton"},"25":{"name":"Tom Ridgewel","ckey":"darksucc","location":"Wasteland","health":40,"job":"NCR Trooper","species":"Human"},"26":{"name":"Unknown","ckey":"alexalbright","location":"Wasteland","health":-771.17,"job":"Legion Prime Decanus","species":"Human"},"27":{"name":"Unknown","ckey":"guilhty","location":"Wasteland","health":-656,"job":"Outlaw","species":"Human"},"28":{"name":"Unknown","ckey":"guilhty","location":"Wasteland","health":-519.96,"job":"Outlaw","species":"Human"},"29":{"name":"Monte Ehret","ckey":"degusta00","location":"Wasteland","health":-100.01,"job":"Wastelander","species":"Human"},"30":{"name":"Unknown","ckey":"nickenzo12345","location":"Wasteland","health":-860.5,"job":"Recruit Legionary","species":"Human"},"31":{"name":"Unknown","ckey":"nickenzo12345","location":"Wasteland","health":-873.57,"job":"Veteran Legionary","species":"Human"},"32":{"name":"Unknown","ckey":"johnegbert3","location":"Wasteland","health":-1256.49,"job":"Veteran Legionary","species":"Human"},"33":{"name":"Unknown","ckey":"johnegbert3","location":"Wasteland","health":-1207.28,"job":"Legion Explorer","species":"Human"},"34":{"name":"Unknown","ckey":"2006f","location":"Wasteland","health":-1226.13,"job":"Doctor","species":"Human"},"35":{"name":"Unknown","ckey":"luciam","location":"Wasteland","health":-484.3,"job":"Wastelander","species":"Human"},"36":{"name":"Valary Lafortune","ckey":"nickenzo12345","location":"Bunker","health":-110,"job":"Outlaw","species":"Human"},"37":{"name":"Vaughn Baxter","ckey":"mollwu","location":"Building","health":100,"job":"Wastelander","species":"Human"},"38":{"name":"Vinny Jowers","ckey":"corvopimpolho","location":"Legion","health":-202.41,"job":"Outlaw","species":"Human"},"39":{"name":"Will Riker","ckey":"xxlucaswesleyxx","location":"Bunker","health":-100,"job":"Citizen","species":"Human"},"40":{"name":"Yuri Stigat","ckey":"jhonatanlima","location":"Wasteland","health":-345.75,"job":"Wastelander","species":"Human"},"41":{"name":"Zak Waldron","ckey":"zircony","location":"North Bunker Elevator","health":-100,"job":"Wastelander","species":"Human"}},"silicons":{"1":{"name":"Sky","ckey":"luciam","location":"Bunker","health":-100,"module":"Engineering"}},"others":{"1":{"name":"Drone (211)","ckey":"hue100","location":"Brotherhood of Steel RnD Department","health":0,"name":"Drone (211)","typepath":"/mob/living/simple_animal/drone"},"2":{"name":"Lenny Callison","ckey":"2006f","location":"Wasteland","health":100,"name":"Lenny Callison","typepath":"/mob/living/brain"},"3":{"name":"Nykix Nywt","ckey":"matheusgp9999","location":"North Bunker Elevator","health":100,"name":"Nykix Nywt","typepath":"/mob/living/brain"}},"npcs":{"Unknown":182,"mouse":1,"legendary deathclaw":1,"alpha feral dog":3,"big horner":2,"brahmin":18,"brahmin calf":5,"cazador":16,"Centaur":21,"chicken":12,"parrot":1,"deathclaw":28,"eyebot":10,"creature":1,"failed experiment":4,"feral dog":15,"feral ghoul":34,"feral ghoul reaver":18,"fireant":24,"Floorbot":1,"gecko":20,"giant ant queen":1,"giant ice spider":1,"giant rad scorpion":15,"giant radscorpion":35,"giant spider":9,"glowing feral ghoul":7,"ghost":1,"Legendary Raider":1,"legendary super mutant":9,"lil' chew-chew":1,"brain":1,"mirelurk":10,"mirelurk baby":51,"mirelurk hunter":5,"molerat":21,"mother deathclaw":8,"mr. gutsy":9,"mr. handy":3,"mr.handy":3,"nightkin":1,"nightkin veteran":1,"nightstalker":5,"Mysterious Medibot":1,"pug":2,"protectron":1,"radroach":62,"Raider":8,"Raider Boss":1,"rat":8,"regal rat":1,"robobrain":2,"sentry bot":2,"Sergeant Sillyhorn":1,"super mutant":50,"Trading Protectron":3,"wanamingo":16,"young cazador":5,"young nightstalker":3}},"ghosts":{"1":{"name":"James Betrayon","ckey":"syndipudim"},"2":{"name":"Jaslene Jenkins","ckey":"n0fun"},"3":{"name":"Luiz Borgos Primeiro","ckey":"luiz20"},"4":{"name":"Montagne Marshall","ckey":"brunoasbahr"},"5":{"name":"Nizin Veerriene","ckey":"nizimgamer"},"6":{"name":"Roderick Malkav","ckey":null},"7":{"name":"Will Riker","ckey":"xxlucaswesleyxx"},"8":{"name":"Zak Waldron","ckey":"zircony"},"9":{"name":"Drone (211)","ckey":"hue100"},"10":{"name":"Rodrigo Weisgarber","ckey":"mastrodonteplays"}},"additional data":{"station integrity":98.6}}
